advance_adb/Exceptions.py
advance_adb/__init__.py
advance_adb/adb.py
advance_adb/analytics.py
advance_adb/app.py
advance_adb/files.py
advance_adb/misc.py
advance_adb/utilities.py
advance_adb/whatsapp.py
advance_adb-0.0.2.dist-info/METADATA
advance_adb-0.0.2.dist-info/WHEEL
advance_adb-0.0.2.dist-info/top_level.txt
advance_adb-0.0.2.dist-info/RECORD
